looker_gen/__init__.py
looker_gen/cli.py
looker_gen/config.py
looker_gen/files.py
looker_gen/generator.py
looker_gen/logging.py
looker_gen/looker.py
looker_gen/project.py
looker_gen/type_mappings.py
looker_gen/types.py
looker_gen-0.1.5.dist-info/entry_points.txt
looker_gen-0.1.5.dist-info/WHEEL
looker_gen-0.1.5.dist-info/METADATA
looker_gen-0.1.5.dist-info/RECORD
